hero_mvc/__init__.py
hero_mvc/main.py
hero_mvc/controller/__init__.py
hero_mvc/controller/controller_hero.py
hero_mvc/model/__init__.py
hero_mvc/model/dto.py
hero_mvc/model/models.py
hero_mvc/repository/__init__.py
hero_mvc/repository/hero_repository.py
hero_mvc/service/__init__.py
hero_mvc/service/hero_service.py
hero_mvc/util/__init__.py
hero_mvc/util/database.py
lib_hero_mvc_ps-0.1.4.dist-info/licenses/LICENSE
lib_hero_mvc_ps-0.1.4.dist-info/METADATA
lib_hero_mvc_ps-0.1.4.dist-info/WHEEL
lib_hero_mvc_ps-0.1.4.dist-info/top_level.txt
lib_hero_mvc_ps-0.1.4.dist-info/RECORD
