Metadata-Version: 2.4
Name: lib_hero_mvc_ps
Version: 0.1.4
Summary: Uma lib MVC simples da Hero com banco de dados em memória.
Author-email: comunisca <lumatavares501@gmail.com>
License: MIT
Project-URL: Homepage, https://github.com/LumaTavares/lib_ps
Requires-Python: >=3.8
License-File: LICENSE
Requires-Dist: fastapi>=0.110.0
Requires-Dist: uvicorn>=0.27.0
Dynamic: license-file
